thelabinstrumentation/__init__.py
thelabinstrumentation/apps.py
thelabinstrumentation/conf.py
thelabinstrumentation/py.typed
thelabinstrumentation/backends/__init__.py
thelabinstrumentation/backends/base.py
thelabinstrumentation/backends/cloudwatch.py
thelabinstrumentation/backends/factory.py
thelabinstrumentation/backends/logging.py
thelabinstrumentation/rq/__init__.py
thelabinstrumentation/rq/apps.py
thelabinstrumentation/rq/daemon.py
thelabinstrumentation/tests/__init__.py
thelabinstrumentation/tests/urls.py
thelabinstrumentation/tests/backends/__init__.py
thelabinstrumentation/tests/backends/test_base.py
thelabinstrumentation/tests/backends/test_cloudwatch.py
thelabinstrumentation/tests/backends/test_factory.py
thelabinstrumentation/tests/backends/test_logging.py
thelabinstrumentation/tests/rq/__init__.py
thelabinstrumentation/tests/rq/test_apps.py
thelabinstrumentation/tests/rq/test_daemon.py
thelabinstrumentation/tests/settings/__init__.py
thelabinstrumentation/tests/settings/sqlite.py
thelab_instrumentation-0.3.0.dist-info/METADATA
thelab_instrumentation-0.3.0.dist-info/WHEEL
thelab_instrumentation-0.3.0.dist-info/licenses/LICENSE
thelab_instrumentation-0.3.0.dist-info/RECORD
