Metadata-Version: 2.4
Name: thelab-instrumentation
Version: 0.3.0
Summary: Shared instrumentation and monitoring code for Django projects
Project-URL: Homepage, https://gitlab.com/thelabnyc/thelab-instrumentation
Project-URL: Documentation, https://gitlab.com/thelabnyc/thelab-instrumentation
Project-URL: Repository, https://gitlab.com/thelabnyc/thelab-instrumentation
Author-email: thelab <thelabdev@thelab.co>
License: ISC
License-File: LICENSE
Requires-Python: >=3.13
Requires-Dist: django-stubs-ext>=5.1.3
Requires-Dist: django<6.0,>=5.2
Requires-Dist: sentry-sdk>=2.31.0
Requires-Dist: typing-extensions>=4.12.0
Provides-Extra: cloudwatch
Requires-Dist: boto3>=1.35.0; extra == 'cloudwatch'
Provides-Extra: rq
Requires-Dist: django-rq>=2.10.0; extra == 'rq'
Requires-Dist: rq>=1.16.0; extra == 'rq'
